neuroglancer_scripts/__init__.py
neuroglancer_scripts/_compressed_segmentation.py
neuroglancer_scripts/_jpeg.py
neuroglancer_scripts/accessor.py
neuroglancer_scripts/chunk_encoding.py
neuroglancer_scripts/data_types.py
neuroglancer_scripts/downscaling.py
neuroglancer_scripts/dyadic_pyramid.py
neuroglancer_scripts/file_accessor.py
neuroglancer_scripts/http_accessor.py
neuroglancer_scripts/mesh.py
neuroglancer_scripts/precomputed_io.py
neuroglancer_scripts/sharded_base.py
neuroglancer_scripts/sharded_file_accessor.py
neuroglancer_scripts/sharded_http_accessor.py
neuroglancer_scripts/transform.py
neuroglancer_scripts/utils.py
neuroglancer_scripts/volume_reader.py
neuroglancer_scripts/scripts/__init__.py
neuroglancer_scripts/scripts/compute_scales.py
neuroglancer_scripts/scripts/convert_chunks.py
neuroglancer_scripts/scripts/generate_scales_info.py
neuroglancer_scripts/scripts/link_mesh_fragments.py
neuroglancer_scripts/scripts/mesh_to_precomputed.py
neuroglancer_scripts/scripts/scale_stats.py
neuroglancer_scripts/scripts/slices_to_precomputed.py
neuroglancer_scripts/scripts/volume_to_precomputed.py
neuroglancer_scripts/scripts/volume_to_precomputed_pyramid.py
neuroglancer_scripts-1.2.0.dist-info/LICENCE.txt
neuroglancer_scripts-1.2.0.dist-info/METADATA
neuroglancer_scripts-1.2.0.dist-info/WHEEL
neuroglancer_scripts-1.2.0.dist-info/entry_points.txt
neuroglancer_scripts-1.2.0.dist-info/top_level.txt
neuroglancer_scripts-1.2.0.dist-info/RECORD
