Metadata-Version: 2.1
Name: neuroglancer-scripts
Version: 1.2.0
Summary: Conversion of images to the Neuroglancer pre-computed format
Home-page: https://github.com/HumanBrainProject/neuroglancer-scripts
Author: Yann Leprince
Author-email: yann.leprince@cea.fr
Keywords: neuroimaging
Classifier: Development Status :: 5 - Production/Stable
Classifier: Environment :: Console
Classifier: Intended Audience :: Science/Research
Classifier: License :: OSI Approved :: MIT License
Classifier: Programming Language :: Python :: 3
Classifier: Programming Language :: Python :: 3.6
Classifier: Programming Language :: Python :: 3.7
Classifier: Programming Language :: Python :: 3.8
Classifier: Programming Language :: Python :: 3.9
Classifier: Programming Language :: Python :: 3.10
Classifier: Programming Language :: Python :: 3.11
Classifier: Programming Language :: Python :: 3.12
Classifier: Topic :: Scientific/Engineering :: Medical Science Apps.
Classifier: Topic :: Scientific/Engineering :: Visualization
Requires-Python: ~=3.6
License-File: LICENCE.txt
Requires-Dist: nibabel >=2
Requires-Dist: numpy >=1.17
Requires-Dist: pillow >=1.1.6
Requires-Dist: requests >=2
Requires-Dist: scikit-image
Requires-Dist: tqdm ~=4.29
Requires-Dist: imagecodecs
Provides-Extra: dev
Requires-Dist: pytest ; extra == 'dev'
Requires-Dist: requests-mock ; extra == 'dev'
Requires-Dist: check-manifest ; extra == 'dev'
Requires-Dist: pep8-naming ; extra == 'dev'
Requires-Dist: pre-commit ; extra == 'dev'
Requires-Dist: pytest-cov ; extra == 'dev'
Requires-Dist: readme-renderer ; extra == 'dev'
Requires-Dist: ruff ; extra == 'dev'
Requires-Dist: sphinx ; extra == 'dev'
Requires-Dist: tox ; extra == 'dev'
Provides-Extra: docs
Requires-Dist: sphinx ; extra == 'docs'
